XStatic_JSEncrypt-2.3.1.1-py2.7-nspkg.pth
XStatic_JSEncrypt-2.3.1.1.dist-info/DESCRIPTION.rst
XStatic_JSEncrypt-2.3.1.1.dist-info/METADATA
XStatic_JSEncrypt-2.3.1.1.dist-info/RECORD
XStatic_JSEncrypt-2.3.1.1.dist-info/WHEEL
XStatic_JSEncrypt-2.3.1.1.dist-info/metadata.json
XStatic_JSEncrypt-2.3.1.1.dist-info/namespace_packages.txt
XStatic_JSEncrypt-2.3.1.1.dist-info/top_level.txt
xstatic/pkg/jsencrypt/__init__.py
xstatic/pkg/jsencrypt/data/jsencrypt.js
