Metadata-Version: 2.0
Name: XStatic-JSEncrypt
Version: 2.3.1.1
Summary: JSEncrypt 2.3.1 (XStatic packaging standard)
Home-page: http://travistidwell.com/jsencrypt/
Author: Rob Cresswell
Author-email: robert.cresswell@outlook.com
License: MIT
Keywords: jsencrypt xstatic
Platform: any
